snipster_tui/__init__.py
snipster_tui/exceptions.py
snipster_tui/models.py
snipster_tui/repo.py
snipster_tui/tui.py
snipster_tui-0.5.3.dist-info/WHEEL
snipster_tui-0.5.3.dist-info/entry_points.txt
snipster_tui-0.5.3.dist-info/METADATA
snipster_tui-0.5.3.dist-info/RECORD
