Metadata-Version: 2.3
Name: snipster-tui
Version: 0.5.3
Summary: snipster-tui is a terminal user interface (TUI) application for managing and browsing code snippets in a local sqlite database.
Author: Razhiel
Author-email: Razhiel <razhiel@gmx.net>
Requires-Dist: alembic>=1.17.2
Requires-Dist: psycopg2-binary>=2.9.11
Requires-Dist: python-decouple>=3.8
Requires-Dist: sqlmodel>=0.0.27
Requires-Dist: textual>=6.10.0
Requires-Python: >=3.13
